plct_bulder_for_sphinx/__init__.py
plct_bulder_for_sphinx/builder/__init__.py
plct_bulder_for_sphinx/builder/plct_builder.py
plct_bulder_for_sphinx/moodle-templates/activities/grade_history.xml
plct_bulder_for_sphinx/moodle-templates/activities/grades.xml
plct_bulder_for_sphinx/moodle-templates/activities/inforef.xml
plct_bulder_for_sphinx/moodle-templates/activities/module.xml
plct_bulder_for_sphinx/moodle-templates/activities/roles.xml
plct_bulder_for_sphinx/moodle-templates/activities/scorm.xml
plct_bulder_for_sphinx/moodle-templates/completion.xml
plct_bulder_for_sphinx/moodle-templates/course/completiondefaults.xml
plct_bulder_for_sphinx/moodle-templates/course/course.xml
plct_bulder_for_sphinx/moodle-templates/course/enrolments.xml
plct_bulder_for_sphinx/moodle-templates/course/inforef.xml
plct_bulder_for_sphinx/moodle-templates/course/roles.xml
plct_bulder_for_sphinx/moodle-templates/files.xml
plct_bulder_for_sphinx/moodle-templates/grade_history.xml
plct_bulder_for_sphinx/moodle-templates/gradebook.xml
plct_bulder_for_sphinx/moodle-templates/groups.xml
plct_bulder_for_sphinx/moodle-templates/moodle_backup.xml
plct_bulder_for_sphinx/moodle-templates/outcomes.xml
plct_bulder_for_sphinx/moodle-templates/questions.xml
plct_bulder_for_sphinx/moodle-templates/roles.xml
plct_bulder_for_sphinx/moodle-templates/scales.xml
plct_bulder_for_sphinx/moodle-templates/sections/inforef.xml
plct_bulder_for_sphinx/moodle-templates/sections/section.xml
plct_bulder_for_sphinx/package/__init__.py
plct_bulder_for_sphinx/package/moodleclasses.py
plct_bulder_for_sphinx/package/package.py
plct_bulder_for_sphinx/package/util.py
plct_bulder_for_sphinx/player/babel-mapping.ini
plct_bulder_for_sphinx/player/content/content.js
plct_bulder_for_sphinx/player/content/petljaRTBundle.js
plct_bulder_for_sphinx/player/locale/sr/LC_MESSAGES/sphinx.po
plct_bulder_for_sphinx/player/player/bundle.js
plct_bulder_for_sphinx/player/player/style-player.css
plct_bulder_for_sphinx/player/player.html
plct_bulder_for_sphinx-0.0.4.dist-info/LICENSE
plct_bulder_for_sphinx-0.0.4.dist-info/METADATA
plct_bulder_for_sphinx-0.0.4.dist-info/WHEEL
plct_bulder_for_sphinx-0.0.4.dist-info/RECORD
