Metadata-Version: 2.1
Name: plct-bulder-for-sphinx
Version: 0.0.4
Summary: Sphinx html builder capable of multiple build targets (scorm, moodle backup, static website).
Author: Petlja
Author-email: team@petlja.com
Requires-Python: >=3.9,<4.0
Classifier: Programming Language :: Python :: 3
Classifier: Programming Language :: Python :: 3.9
Classifier: Programming Language :: Python :: 3.10
Classifier: Programming Language :: Python :: 3.11
Classifier: Programming Language :: Python :: 3.12
Requires-Dist: Sphinx (==7.1.2)
Requires-Dist: cyrtranslit
Requires-Dist: docutils
Requires-Dist: jinja2
